{
    "name": "Customer",
    "fields": [
        {
            "fieldName": "name",
            "fieldType": "String"
        },
        {
            "fieldName": "lastName",
            "fieldType": "String"
        }
    ],
    "relationships": [
        {
            "relationshipType": "one-to-many",
            "otherEntityName": "product",
            "otherEntityRelationshipName": "customer",
            "javadoc": "A relationship",
            "relationshipName": "product"
        }
    ],
    "changelogDate": "20200205113252",
    "entityTableName": "customer",
    "dto": "no",
    "pagination": "no",
    "service": "serviceImpl",
    "jpaMetamodelFiltering": false,
    "fluentMethods": true,
    "readOnly": false,
    "clientRootFolder": "",
    "applications": "*"
}